cppwriter/__init__.py
cppwriter/block.py
cppwriter/block_enum.py
cppwriter/block_file.py
cppwriter/block_function.py
cppwriter-0.0.4.dist-info/LICENSE
cppwriter-0.0.4.dist-info/METADATA
cppwriter-0.0.4.dist-info/WHEEL
cppwriter-0.0.4.dist-info/top_level.txt
cppwriter-0.0.4.dist-info/RECORD
