Metadata-Version: 2.1
Name: cppwriter
Version: 0.0.4
Summary: C++ code writer library
Author-email: Mikhael Khrustik <misha@myrt.co>
License: MIT
Keywords: cpp,arduino,c++
Classifier: Development Status :: 5 - Production/Stable
Classifier: Intended Audience :: Developers
Classifier: License :: OSI Approved :: MIT License
Classifier: Programming Language :: Python :: 3.10
Classifier: Programming Language :: Python :: 3.11
Classifier: Programming Language :: Python :: 3.12
Requires-Python: >=3.10
License-File: LICENSE
